co2_import/__init__.py
co2_import/cli/cli.py
co2_import/const.py
co2_import/data/odoo.conf
co2_import/exceptions.py
co2_import/handler.py
co2_import/utils/git.py
co2_import/utils/repos.py
co2_import-0.1.0.dist-info/METADATA
co2_import-0.1.0.dist-info/WHEEL
co2_import-0.1.0.dist-info/RECORD
